FlowMeCore.dll
FlowMePy.cp310-win_amd64.pyd
Qt6Concurrent.dll
Qt6Core.dll
Qt6Gui.dll
Qt6PrintSupport.dll
Qt6Widgets.dll
opencv_world4110.dll
cloud/2014-1060-2014-1060KM 1001.fcs.yml
cloud/2014-1174-2014-1174KM 1001.fcs.yml
cloud/2014-1232-2014-1232KM 1001.fcs.yml
cloud/2014-1240-2014-1240KM 1001.fcs.yml
cloud/2014-1243-2014-1243KM 1001.fcs.yml
cloud/2014-1404-2014-1404KM 1001.fcs.yml
cloud/2014-1585-2014-1585KM 1001.fcs.yml
cloud/2014-1592-2014-1592KM 1001.fcs.yml
cloud/2014-1722-2014-1722KM 1001.fcs.yml
cloud/2014-1751-2014-1751KM 1001.fcs.yml
cloud/2014-1877-2014-1877KM 1001.fcs.yml
cloud/2014-1921-2014-1921KM 1001.fcs.yml
cloud/2014-2714-2014-2714KM 1001.fcs.yml
cloud/2014-2945-2014-2945KM 1001.fcs.yml
cloud/2014-2994-2014-2994KM 1001.fcs.yml
cloud/2014-3020-2014-3020KM 1001.fcs.yml
cloud/2014-3031-2014-3031KM 1001.fcs.yml
cloud/2014-3399-2014-3399KM 1001.fcs.yml
cloud/2014-3427-2014-3427KM 1001.fcs.yml
cloud/2014-3501-2014-3501KM 1001.fcs.yml
cloud/2014-3946-2014-3946KM 1001.fcs.yml
cloud/2014-3953-2014-3953KM 1001.fcs.yml
cloud/2014-4021-2014-4021KM 1001.fcs.yml
cloud/2014-4055-2014-4055KM 1001.fcs.yml
cloud/2014-4096-2014-4096KM 1001.fcs.yml
cloud/2014-4564-2014-4564KM 1001.fcs.yml
cloud/2015-0071-2015-0071KM 1001.fcs.yml
cloud/2015-0209-2015-0209KM 1001.fcs.yml
cloud/2015-0388-2015-0388KM 1001.fcs.yml
cloud/2015-0415-2015-0415KM 1001.fcs.yml
cloud/2015-0451-2015-0451KM 1001.fcs.yml
cloud/2015-0496-2015-0496KM 1001.fcs.yml
cloud/2015-0605-2015-0605KM 1001.fcs.yml
cloud/2015-0704-2015-0704KM 1001.fcs.yml
cloud/2015-0758-2015-0758KM 1001.fcs.yml
cloud/2015-0769-2015-0769KM 1001.fcs.yml
cloud/2015-0789-2015-0789KM 1001.fcs.yml
cloud/2015-0934-2015-0934KM 1001.fcs.yml
cloud/2015-0943-2015-0943KM 1001.fcs.yml
cloud/2015-1197-2015-1197KM 1001.fcs.yml
cloud/2015-1202-2015-1202KM 1001.fcs.yml
cloud/2015-1209-2015-1209KM 1001.fcs.yml
cloud/2015-1383-2015-1383KM 1001.fcs.yml
cloud/2015-1388-2015-1388KM 1001.fcs.yml
cloud/2015-1434-2015-1434KM 1001.fcs.yml
flowmepy-0.4.0.dist-info/licenses/LICENSE
flowmepy-0.4.0.dist-info/METADATA
flowmepy-0.4.0.dist-info/WHEEL
flowmepy-0.4.0.dist-info/top_level.txt
flowmepy-0.4.0.dist-info/RECORD
