Metadata-Version: 2.4
Name: flowmepy
Version: 0.4.0
Summary: a C++ FCS Loader
Author: Markus Diem, Lisa Weijler, Matthias Woedlinger, Florian Kowarsch, Peter Buchegger
Author-email: pbuchegger@cvl.tuwien.ac.at
License-File: LICENSE
Requires-Dist: numpy>=1.17.4
Requires-Dist: pandas>=0.24.2
Requires-Dist: cmake!=3.16.3
Requires-Dist: setuptools<81.0.0,>=80.0.0
Dynamic: author
Dynamic: author-email
Dynamic: description
Dynamic: description-content-type
Dynamic: license-file
Dynamic: requires-dist
Dynamic: summary
